{
  "info": {
    "cutoff": 0.0,
    "cutoff deviation": 0,
    "metagame": "gen5ubers",
    "number of battles": 12
  },
  "data": {
    "Durant": {
      "Abilities": { "truant": 1.0 },
      "Items": { "focussash": 1.0 },
      "Raw count": 1,
      "Spreads": { "Rash:4/252/0/0/0/252": 1.0 },
      "Checks and Counters": {},
      "Moves": {
        "xscissor": 1.0,
        "superpower": 1.0,
        "substitute": 1.0,
        "entrainment": 1.0
      },
      "Teammates": {
        "Smeargle": 0.9166667,
        "Floatzel": 0.9583333,
        "Dugtrio": 0.9166667,
        "Hydreigon": 0.9583333,
        "Slowbro": 0.9583333
      }
    },
    "Giratina": {
      "Abilities": { "pressure": 5.0 },
      "Items": { "nothing": 1.0, "leftovers": 4.0 },
      "Raw count": 5,
      "Spreads": {
        "Careful:252/4/0/0/252/0": 1.0,
        "Hardy:84/84/84/84/84/84": 1.0,
        "Impish:248/0/0/0/240/20": 3.0
      },
      "Checks and Counters": {},
      "Moves": {
        "dragontail": 2.0,
        "earthpower": 1.0,
        "roar": 3.0,
        "rest": 4.0,
        "sleeptalk": 4.0,
        "willowisp": 4.0,
        "outrage": 1.0,
        "dracometeor": 1.0
      },
      "Teammates": {
        "Mewtwo": 0.16666650000000005,
        "Gliscor": 1.5833335,
        "Palkia": 1.75,
        "Ampharos": 0.7916665,
        "Zekrom": -0.25,
        "Reshiram": -0.04166650000000005,
        "Blaziken": 0.5833335,
        "Kyurem-White": 0.375,
        "Forretress": 0.5833335,
        "Tyranitar": 1.375,
        "Genesect": 0.375,
        "Groudon": -0.04166650000000005,
        "Ferrothorn": 1.375,
        "Excadrill": 0.9583335
      }
    },
    "Palkia": {
      "Abilities": { "pressure": 8.0, "telepathy": 1.0 },
      "Items": {
        "rockyhelmet": 1.0,
        "habanberry": 1.0,
        "choicescarf": 4.0,
        "choicespecs": 1.0,
        "lustrousorb": 2.0
      },
      "Raw count": 9,
      "Spreads": {
        "Naive:0/0/4/252/0/252": 1.0,
        "Timid:5/0/0/252/0/252": 1.0,
        "Timid:4/0/0/252/0/252": 5.0,
        "Timid:0/4/0/252/0/252": 1.0,
        "Hardy:104/144/92/144/24/0": 1.0
      },
      "Checks and Counters": {},
      "Moves": {
        "surf": 6.0,
        "dragontail": 1.0,
        "thunderbolt": 1.0,
        "earthpower": 1.0,
        "hypervoice": 1.0,
        "dragonpulse": 1.0,
        "thunder": 6.0,
        "spacialrend": 8.0,
        "aurasphere": 3.0,
        "hydropump": 1.0,
        "fireblast": 4.0,
        "flamethrower": 3.0
      },
      "Teammates": {
        "Kyurem-White": -0.125,
        "Arceus-Ghost": 0.25000029999999995,
        "Gliscor": 1.2500003,
        "Giratina": 1.4999997,
        "Giratina-Origin": 0.49999970000000005,
        "Kyogre": -1.6250003,
        "Zekrom": -1.25,
        "Arceus": -0.8749997,
        "Deoxys-Attack": 0.25000029999999995,
        "Reshiram": 0.12500029999999995,
        "Mewtwo": -0.5000003,
        "Forretress": 1.2500003,
        "Tyranitar": 0.875,
        "Kyurem-Black": 0.25000029999999995,
        "Dialga": 0.6249997,
        "Groudon": 0.12500029999999995,
        "Ferrothorn": 0.875,
        "Darkrai": -0.8749997,
        "Excadrill": 1.1250003
      }
    },
    "Weavile": {
      "Abilities": { "pressure": 1.0, "pickpocket": 1.0 },
      "Items": { "nothing": 1.0, "lifeorb": 1.0 },
      "Raw count": 2,
      "Spreads": { "Jolly:4/252/0/0/0/252": 1.0, "Hardy:0/252/0/0/0/252": 1.0 },
      "Checks and Counters": {},
      "Moves": {
        "iceshard": 1.0,
        "icebeam": 1.0,
        "blizzard": 1.0,
        "calmmind": 1.0,
        "icepunch": 1.0,
        "lowkick": 1.0,
        "pursuit": 1.0,
        "honeclaws": 1.0
      },
      "Teammates": {
        "Gothitelle": 0.9166666,
        "Arceus": 0.5833334,
        "Shedinja": 0.9166666,
        "Steelix": 0.9166666,
        "Kyogre": 0.4166666,
        "Omastar": 0.9166666,
        "Garchomp": 0.9166666,
        "Azumarill": 0.9166666,
        "Shaymin-Sky": 0.8333334,
        "Excadrill": 0.5833334
      }
    },
    "Zekrom": {
      "Abilities": { "teravolt": 9.0 },
      "Items": {
        "airballoon": 2.0,
        "leftovers": 1.0,
        "choicescarf": 1.0,
        "nothing": 1.0,
        "zapplate": 2.0,
        "razorclaw": 1.0,
        "choiceband": 1.0
      },
      "Raw count": 9,
      "Spreads": {
        "Naughty:252/252/0/4/0/0": 2.0,
        "Hardy:252/0/0/0/104/152": 1.0,
        "Hardy:84/84/84/84/84/84": 2.0,
        "Timid:84/84/84/84/84/84": 1.0,
        "Jolly:4/252/0/0/0/252": 1.0,
        "Lonely:0/252/0/0/4/252": 1.0,
        "Hardy:76/72/124/120/88/28": 1.0
      },
      "Checks and Counters": {},
      "Moves": {
        "fly": 1.0,
        "crunch": 2.0,
        "earthpower": 1.0,
        "fusionbolt": 4.0,
        "boltstrike": 8.0,
        "flashcannon": 2.0,
        "focusblast": 1.0,
        "dragontail": 1.0,
        "haze": 1.0,
        "chargebeam": 2.0,
        "outrage": 2.0,
        "dragonclaw": 3.0,
        "psychic": 1.0,
        "stoneedge": 1.0,
        "dracometeor": 5.0
      },
      "Teammates": {
        "Giratina": -0.5000003,
        "Palkia": -1.25,
        "Dragonite": 0.6249997,
        "Darmanitan": 0.6249997,
        "Kyogre": -1.6250003,
        "Raichu": 0.25000029999999995,
        "Charizard": 0.25000029999999995,
        "Rayquaza": -0.8749997,
        "Reshiram": -0.8749997,
        "Blaziken": 1.2500003,
        "Kyurem-White": 0.875,
        "Genesect": -0.125,
        "Kyurem-Black": 0.25000029999999995,
        "empty": 0.0,
        "Smeargle": 0.25000029999999995,
        "Arceus": 0.12500029999999995,
        "Giratina-Origin": -0.5000003,
        "Bisharp": 0.6249997,
        "Krookodile": 0.6249997,
        "Carracosta": 0.6249997,
        "Serperior": 0.25000029999999995,
        "Ampharos": 0.6249997,
        "Victini": 0.6249997,
        "Dialga": 0.6249997,
        "Darkrai": 0.12500029999999995
      }
    },
    "Arceus": {
      "Abilities": { "multitype": 5.0 },
      "Items": {
        "leftovers": 1.0,
        "silkscarf": 1.0,
        "quickclaw": 1.0,
        "lumberry": 1.0,
        "chestoberry": 1.0
      },
      "Raw count": 5,
      "Spreads": {
        "Adamant:252/252/0/0/0/4": 1.0,
        "Adamant:248/252/0/0/0/8": 1.0,
        "Hardy:124/112/80/104/88/0": 1.0,
        "Hardy:116/0/0/200/64/112": 1.0,
        "Adamant:244/252/0/0/0/12": 1.0
      },
      "Checks and Counters": {},
      "Moves": {
        "blizzard": 1.0,
        "roar": 1.0,
        "heatwave": 1.0,
        "brickbreak": 1.0,
        "shadowclaw": 2.0,
        "extremespeed": 4.0,
        "swordsdance": 2.0,
        "stealthrock": 1.0,
        "avalanche": 1.0,
        "chargebeam": 1.0,
        "willowisp": 1.0,
        "energyball": 1.0,
        "recover": 1.0,
        "earthquake": 2.0
      },
      "Teammates": {
        "Latios": 0.7916665,
        "Gothitelle": 0.7916665,
        "Palkia": -0.25,
        "Giratina-Origin": 0.16666650000000005,
        "Weavile": 0.5833335,
        "Deoxys-Attack": 0.5833335,
        "Zekrom": 0.75,
        "Rayquaza": 0.9583335,
        "Blaziken": 0.5833335,
        "Kyogre": 2.5416665,
        "Omastar": 0.7916665,
        "Espeon": 0.5833335,
        "empty": 0.0,
        "Victini": 0.7916665,
        "Kyurem-Black": 0.5833335,
        "Ferrothorn": 0.375,
        "Darkrai": -0.04166650000000005,
        "Shaymin-Sky": 0.5833335,
        "Excadrill": -0.04166650000000005
      }
    },
    "Slowbro": {
      "Abilities": { "oblivious": 1.0 },
      "Items": { "nothing": 1.0 },
      "Raw count": 1,
      "Spreads": { "Calm:252/0/4/0/252/0": 1.0 },
      "Checks and Counters": {},
      "Moves": {
        "calmmind": 1.0,
        "irondefense": 1.0,
        "block": 1.0,
        "slackoff": 1.0
      },
      "Teammates": {
        "Smeargle": 0.9166667,
        "Floatzel": 0.9583333,
        "Durant": 0.9583333,
        "Hydreigon": 0.9583333,
        "Dugtrio": 0.9166667
      }
    },
    "Tyranitar": {
      "Abilities": { "sandstream": 5.0 },
      "Items": { "chopleberry": 1.0, "apicotberry": 1.0, "lumberry": 3.0 },
      "Raw count": 5,
      "Spreads": {
        "Adamant:4/252/0/0/0/252": 1.0,
        "Adamant:252/64/0/0/180/12": 3.0,
        "Hardy:84/84/84/84/84/84": 1.0
      },
      "Checks and Counters": {},
      "Moves": {
        "flamethrower": 1.0,
        "blizzard": 1.0,
        "foulplay": 1.0,
        "dragondance": 1.0,
        "earthquake": 2.0,
        "stealthrock": 4.0,
        "pursuit": 3.0,
        "stoneedge": 4.0,
        "superpower": 3.0
      },
      "Teammates": {
        "Terrakion": 0.7916665,
        "Gliscor": 1.5833335,
        "Giratina": 1.1666665,
        "Palkia": 0.75,
        "Dugtrio": 0.5833335,
        "Landorus": 0.7916665,
        "Heatran": 0.7916665,
        "Ferrothorn": 1.375,
        "Excadrill": 1.9583335
      }
    },
    "Heatran": {
      "Abilities": { "flashfire": 1.0 },
      "Items": { "choicescarf": 1.0 },
      "Raw count": 1,
      "Spreads": { "Quiet:252/0/0/252/4/0": 1.0 },
      "Checks and Counters": {},
      "Moves": {
        "flashcannon": 1.0,
        "eruption": 1.0,
        "earthpower": 1.0,
        "darkpulse": 1.0
      },
      "Teammates": {
        "Landorus": 0.9583333,
        "Terrakion": 0.9583333,
        "Tyranitar": 0.875,
        "Dugtrio": 0.9166667,
        "Excadrill": 0.7916667
      }
    },
    "Mewtwo": {
      "Abilities": { "pressure": 6.0 },
      "Items": {
        "leftovers": 3.0,
        "lifeorb": 1.0,
        "sitrusberry": 1.0,
        "mindplate": 1.0
      },
      "Raw count": 6,
      "Spreads": {
        "Timid:0/0/4/252/0/252": 4.0,
        "Timid:4/0/0/252/0/252": 1.0,
        "Hardy:0/0/252/0/0/252": 1.0
      },
      "Checks and Counters": {},
      "Moves": {
        "blizzard": 1.0,
        "taunt": 2.0,
        "psystrike": 5.0,
        "calmmind": 4.0,
        "aurasphere": 3.0,
        "solarbeam": 1.0,
        "icebeam": 4.0,
        "thunder": 2.0,
        "fireblast": 1.0,
        "flamethrower": 1.0
      },
      "Teammates": {
        "Giratina": -2.0000000011677344e-7,
        "Palkia": -0.5,
        "Giratina-Origin": 0.9999997999999999,
        "Ho-Oh": 1.5000002000000001,
        "Regigigas": 0.7499998,
        "Rayquaza": -0.24999979999999988,
        "Reshiram": -0.24999979999999988,
        "Umbreon": 1.5000002000000001,
        "Forretress": 0.5000002,
        "Groudon": 1.7500002000000001,
        "Darkrai": -0.24999979999999988,
        "Blissey": 1.5000002000000001,
        "Deoxys-Speed": 0.5000002,
        "Charizard": 0.5000002
      }
    },
    "Deoxys-Speed": {
      "Abilities": { "pressure": 3.0 },
      "Items": { "focussash": 1.0, "leftovers": 1.0, "mindplate": 1.0 },
      "Raw count": 3,
      "Spreads": {
        "Jolly:252/4/0/0/0/252": 1.0,
        "Hardy:0/0/252/0/0/252": 1.0,
        "Timid:248/0/8/0/0/252": 1.0
      },
      "Checks and Counters": {},
      "Moves": {
        "spikes": 2.0,
        "darkpulse": 1.0,
        "zapcannon": 1.0,
        "taunt": 2.0,
        "focuspunch": 1.0,
        "focusblast": 1.0,
        "stealthrock": 2.0,
        "psychoboost": 1.0,
        "superpower": 1.0
      },
      "Teammates": {
        "Mewtwo": 0.49999989999999994,
        "Charizard": 0.7500001000000001,
        "Regigigas": 0.8749998999999999,
        "Rayquaza": 1.3750001,
        "Kyogre": 0.12499989999999994,
        "Genesect": 0.625,
        "Arceus-Ghost": 0.7500001000000001,
        "Darkrai": 0.37500010000000006,
        "Kingdra": 0.8749998999999999
      }
    },
    "Terrakion": {
      "Abilities": { "justified": 2.0 },
      "Items": { "brightpowder": 1.0, "choiceband": 1.0 },
      "Raw count": 2,
      "Spreads": { "Jolly:0/252/0/0/4/252": 1.0, "Hardy:0/0/252/0/0/252": 1.0 },
      "Checks and Counters": {},
      "Moves": {
        "focusblast": 1.0,
        "closecombat": 1.0,
        "ironhead": 1.0,
        "stoneedge": 2.0,
        "earthquake": 2.0,
        "block": 1.0
      },
      "Teammates": {
        "Landorus": 0.9166666,
        "Heatran": 0.9166666,
        "Tyranitar": 0.75,
        "Dugtrio": 0.8333334,
        "Excadrill": 0.5833334
      }
    },
    "Arceus-Ghost": {
      "Abilities": { "multitype": 2.0 },
      "Items": { "spookyplate": 2.0 },
      "Raw count": 2,
      "Spreads": { "Timid:252/0/0/4/0/252": 1.0, "Timid:248/0/0/8/0/252": 1.0 },
      "Checks and Counters": {},
      "Moves": {
        "focusblast": 1.0,
        "recover": 2.0,
        "judgment": 2.0,
        "flamethrower": 1.0,
        "calmmind": 2.0
      },
      "Teammates": {
        "Palkia": 0.5,
        "Rayquaza": 0.5833334,
        "Reshiram": 0.5833334,
        "Kyogre": 0.4166666,
        "Forretress": 0.8333334,
        "Genesect": 0.75,
        "Groudon": 0.5833334,
        "Kyurem-Black": 0.8333334,
        "Deoxys-Speed": 0.8333334,
        "Kingdra": 0.9166666
      }
    },
    "Gliscor": {
      "Abilities": { "poisonheal": 3.0 },
      "Items": { "toxicorb": 3.0 },
      "Raw count": 3,
      "Spreads": { "Jolly:252/0/40/0/0/216": 3.0 },
      "Checks and Counters": {},
      "Moves": {
        "toxic": 3.0,
        "taunt": 3.0,
        "earthquake": 3.0,
        "substitute": 3.0
      },
      "Teammates": {
        "Ferrothorn": 1.625,
        "Tyranitar": 1.625,
        "Giratina": 1.4999999,
        "Palkia": 1.25,
        "Excadrill": 1.3750001
      }
    },
    "Charizard": {
      "Abilities": { "blaze": 3.0 },
      "Items": { "nothing": 1.0, "flameplate": 1.0, "firegem": 1.0 },
      "Raw count": 3,
      "Spreads": {
        "Hardy:0/0/252/0/4/252": 1.0,
        "Hasty:108/108/104/84/84/20": 1.0,
        "Hasty:0/252/0/4/0/252": 1.0
      },
      "Checks and Counters": {},
      "Moves": {
        "overheat": 2.0,
        "dragonrush": 1.0,
        "focuspunch": 1.0,
        "heatwave": 1.0,
        "flareblitz": 2.0,
        "outrage": 2.0,
        "dragonclaw": 1.0,
        "fireblast": 2.0
      },
      "Teammates": {
        "Raichu": 0.7500001000000001,
        "Zekrom": 0.25,
        "Regigigas": 0.8749998999999999,
        "Rayquaza": 0.37500010000000006,
        "Reshiram": 0.37500010000000006,
        "Serperior": 0.7500001000000001,
        "Darkrai": 0.37500010000000006,
        "Mewtwo": 0.49999989999999994,
        "Dragonite": 0.8749998999999999,
        "Deoxys-Speed": 0.7500001000000001
      }
    },
    "Ampharos": {
      "Abilities": { "static": 1.0 },
      "Items": { "nothing": 1.0 },
      "Raw count": 1,
      "Spreads": { "Hardy:84/84/84/84/84/84": 1.0 },
      "Checks and Counters": {},
      "Moves": {
        "electroball": 1.0,
        "discharge": 1.0,
        "chargebeam": 1.0,
        "cottonguard": 1.0
      },
      "Teammates": {
        "Zekrom": 0.75,
        "Blaziken": 0.9166667,
        "Giratina": 0.8333333,
        "Genesect": 0.875,
        "Kyurem-White": 0.875
      }
    },
    "Rayquaza": {
      "Abilities": { "airlock": 7.0 },
      "Items": {
        "leftovers": 1.0,
        "lifeorb": 1.0,
        "choicescarf": 1.0,
        "dracoplate": 1.0,
        "zapplate": 1.0,
        "dragonfang": 1.0,
        "whiteherb": 1.0
      },
      "Raw count": 7,
      "Spreads": {
        "Hardy:68/0/224/0/148/68": 1.0,
        "Mild:252/4/0/252/0/0": 1.0,
        "Adamant:32/252/8/0/0/216": 1.0,
        "Jolly:4/252/0/0/0/252": 1.0,
        "Lax:112/80/144/76/96/0": 1.0,
        "Hardy:0/0/4/0/252/252": 1.0,
        "Lonely:252/252/0/4/0/0": 1.0
      },
      "Checks and Counters": {},
      "Moves": {
        "flamethrower": 1.0,
        "blizzard": 1.0,
        "dragonpulse": 1.0,
        "thunder": 3.0,
        "extremespeed": 4.0,
        "aerialace": 1.0,
        "swordsdance": 1.0,
        "ironhead": 1.0,
        "avalanche": 1.0,
        "waterfall": 1.0,
        "vcreate": 5.0,
        "airslash": 1.0,
        "outrage": 1.0,
        "dragonclaw": 2.0,
        "dracometeor": 4.0
      },
      "Teammates": {
        "Latios": 0.7083330999999999,
        "Mewtwo": -0.16666690000000006,
        "Regigigas": 0.7083330999999999,
        "Raichu": 0.41666690000000006,
        "Charizard": 0.41666690000000006,
        "Arceus-Ghost": 0.41666690000000006,
        "Zekrom": -0.75,
        "Arceus": 0.5416669000000001,
        "Reshiram": -0.45833309999999994,
        "Blaziken": 0.41666690000000006,
        "Kyogre": 0.9583330999999999,
        "Darkrai": 0.5416669000000001,
        "Espeon": 1.4166669,
        "Serperior": 0.41666690000000006,
        "Genesect": 0.125,
        "Ferrothorn": 0.125,
        "Arceus-Ice": 0.7083330999999999,
        "Deoxys-Speed": 1.4166669,
        "Kingdra": 0.7083330999999999
      }
    },
    "Reshiram": {
      "Abilities": { "turboblaze": 6.0 },
      "Items": {
        "dragonfang": 1.0,
        "lifeorb": 1.0,
        "choicescarf": 1.0,
        "firegem": 1.0,
        "leftovers": 1.0,
        "nothing": 1.0
      },
      "Raw count": 6,
      "Spreads": {
        "Modest:252/0/0/252/4/0": 1.0,
        "Timid:4/0/0/252/0/252": 1.0,
        "Mild:252/4/0/252/0/0": 2.0,
        "Hardy:84/84/84/84/84/84": 1.0,
        "Hasty:0/4/0/252/0/252": 1.0
      },
      "Checks and Counters": {},
      "Moves": {
        "dragontail": 1.0,
        "earthpower": 2.0,
        "dragonpulse": 3.0,
        "blueflare": 5.0,
        "crunch": 1.0,
        "flamethrower": 1.0,
        "outrage": 2.0,
        "flamecharge": 2.0,
        "fireblast": 1.0,
        "psychic": 1.0,
        "dracometeor": 4.0,
        "extrasensory": 1.0
      },
      "Teammates": {
        "Lugia": 0.5000002,
        "Raichu": 1.5000002000000001,
        "Charizard": 0.5000002,
        "Palkia": 0.5,
        "Kyogre": -0.7500002000000001,
        "Rayquaza": -0.24999979999999988,
        "Zekrom": -0.5,
        "Deoxys-Attack": 0.5000002,
        "Darkrai": -0.24999979999999988,
        "Serperior": 1.5000002000000001,
        "Mewtwo": -2.0000000011677344e-7,
        "Forretress": 1.5000002000000001,
        "Espeon": 0.5000002,
        "Kyurem-Black": 0.5000002,
        "Groudon": 1.7500002000000001,
        "Dragonite": 0.7499998,
        "Arceus-Ghost": 0.5000002,
        "Arceus-Ice": 0.7499998,
        "Giratina": -2.0000000011677344e-7
      }
    },
    "Blaziken": {
      "Abilities": { "speedboost": 1.0, "blaze": 2.0 },
      "Items": { "nothing": 2.0, "firegem": 1.0 },
      "Raw count": 3,
      "Spreads": {
        "Sassy:64/52/52/44/44/252": 1.0,
        "Hardy:132/0/80/40/104/108": 1.0,
        "Hardy:84/84/84/84/84/84": 1.0
      },
      "Checks and Counters": {},
      "Moves": {
        "dynamicpunch": 1.0,
        "blazekick": 3.0,
        "heatwave": 1.0,
        "brickbreak": 2.0,
        "focusblast": 1.0,
        "aerialace": 1.0,
        "flareblitz": 1.0,
        "flamecharge": 1.0,
        "earthquake": 1.0
      },
      "Teammates": {
        "Giratina": 0.49999989999999994,
        "Zekrom": 1.25,
        "Arceus": 0.37500010000000006,
        "Rayquaza": 0.37500010000000006,
        "Kyurem-White": 0.625,
        "Ampharos": 0.8749998999999999,
        "Genesect": 0.625,
        "Kyogre": 0.12499989999999994,
        "Darkrai": 0.37500010000000006
      }
    },
    "Kyurem-White": {
      "Abilities": { "turboblaze": 4.0 },
      "Items": {
        "nothing": 1.0,
        "leftovers": 1.0,
        "choicescarf": 1.0,
        "choicespecs": 1.0
      },
      "Raw count": 4,
      "Spreads": {
        "Modest:0/0/4/252/0/252": 1.0,
        "Timid:0/0/4/252/0/252": 1.0,
        "Mild:252/4/0/252/0/0": 1.0,
        "Hardy:84/84/84/84/84/84": 1.0
      },
      "Checks and Counters": {},
      "Moves": {
        "fly": 1.0,
        "earthpower": 1.0,
        "dragonpulse": 3.0,
        "focusblast": 1.0,
        "icebeam": 2.0,
        "fusionflare": 3.0,
        "iceburn": 1.0,
        "dracometeor": 2.0,
        "": 1.0
      },
      "Teammates": {
        "Lugia": 0.6666668,
        "Giratina": 0.3333332,
        "Palkia": 0.0,
        "Giratina-Origin": 0.3333332,
        "Zekrom": 1.0,
        "Blaziken": 0.6666668,
        "Kyogre": -0.1666668,
        "Ampharos": 0.8333332,
        "Genesect": 1.5,
        "Dialga": 0.8333332,
        "Darkrai": 1.1666668,
        "Shaymin-Sky": 0.6666668
      }
    },
    "Exeggutor": {
      "Abilities": { "harvest": 1.0 },
      "Items": { "leftovers": 1.0 },
      "Raw count": 1,
      "Spreads": { "Modest:252/0/0/252/4/0": 1.0 },
      "Checks and Counters": {},
      "Moves": {
        "hypnosis": 1.0,
        "leafstorm": 1.0,
        "solarbeam": 1.0,
        "extrasensory": 1.0
      },
      "Teammates": {
        "Machamp": 0.9583333,
        "Arcanine": 0.9583333,
        "Alakazam": 0.9583333,
        "Pidgeot": 0.9583333,
        "Blastoise": 0.9583333
      }
    },
    "Garchomp": {
      "Abilities": { "roughskin": 1.0, "sandveil": 1.0 },
      "Items": { "nothing": 1.0, "choiceband": 1.0 },
      "Raw count": 2,
      "Spreads": {
        "Hardy:84/80/100/100/100/44": 1.0,
        "Hardy:156/252/0/0/0/100": 1.0
      },
      "Checks and Counters": {},
      "Moves": {
        "dragontail": 1.0,
        "earthpower": 1.0,
        "dragonpulse": 1.0,
        "dragonrush": 1.0,
        "swordsdance": 1.0,
        "firefang": 1.0,
        "dracometeor": 2.0
      },
      "Teammates": {
        "Weavile": 0.8333334,
        "Azumarill": 0.9166666,
        "Shedinja": 0.9166666,
        "Steelix": 0.9166666,
        "Excadrill": 0.5833334
      }
    },
    "Genesect": {
      "Abilities": { "download": 5.0 },
      "Items": {
        "nothing": 1.0,
        "dousedrive": 1.0,
        "choicescarf": 1.0,
        "quickclaw": 1.0,
        "flameplate": 1.0
      },
      "Raw count": 5,
      "Spreads": {
        "Naive:0/252/0/4/0/252": 1.0,
        "Timid:0/0/0/252/4/252": 1.0,
        "Relaxed:124/84/132/112/56/0": 1.0,
        "Hardy:84/84/84/84/84/84": 1.0,
        "Hasty:0/252/0/4/0/252": 1.0
      },
      "Checks and Counters": {},
      "Moves": {
        "uturn": 1.0,
        "explosion": 1.0,
        "darkpulse": 1.0,
        "gigadrain": 1.0,
        "gunkshot": 1.0,
        "flashcannon": 1.0,
        "thunderbolt": 2.0,
        "extremespeed": 1.0,
        "shadowclaw": 1.0,
        "technoblast": 1.0,
        "icebeam": 1.0,
        "ironhead": 1.0,
        "energyball": 1.0,
        "bugbuzz": 2.0,
        "psychic": 1.0,
        "flamethrower": 3.0
      },
      "Teammates": {
        "Kyurem-White": 1.375,
        "Lugia": 0.5833335,
        "Giratina": 0.16666650000000005,
        "Zekrom": -0.25,
        "Rayquaza": -0.04166650000000005,
        "Blaziken": 0.5833335,
        "Kyogre": 0.5416665,
        "Ampharos": 0.7916665,
        "Shaymin-Sky": 0.5833335,
        "Arceus-Ghost": 0.5833335,
        "Darkrai": -0.04166650000000005,
        "Deoxys-Speed": 0.5833335,
        "Kingdra": 0.7916665
      }
    },
    "Blastoise": {
      "Abilities": { "torrent": 2.0 },
      "Items": { "nothing": 1.0, "leftovers": 1.0 },
      "Raw count": 2,
      "Spreads": {
        "Mild:252/4/0/252/0/0": 1.0,
        "Modest:76/48/44/40/48/252": 1.0
      },
      "Checks and Counters": {},
      "Moves": {
        "hydrocannon": 1.0,
        "bite": 1.0,
        "waterpulse": 1.0,
        "bodyslam": 1.0,
        "rapidspin": 1.0,
        "hydropump": 2.0,
        "earthquake": 1.0
      },
      "Teammates": {
        "Machamp": 0.9166666,
        "Arcanine": 0.9166666,
        "Exeggutor": 0.9166666,
        "Alakazam": 0.9166666,
        "Pidgeot": 0.9166666
      }
    },
    "Kyurem-Black": {
      "Abilities": { "teravolt": 3.0 },
      "Items": { "electricgem": 1.0, "choicescarf": 1.0, "quickclaw": 1.0 },
      "Raw count": 3,
      "Spreads": {
        "Adamant:4/252/0/0/0/252": 1.0,
        "Rash:252/4/0/252/0/0": 1.0,
        "Hardy:0/252/0/224/0/0": 1.0
      },
      "Checks and Counters": {},
      "Moves": {
        "earthpower": 1.0,
        "blizzard": 2.0,
        "dragonpulse": 1.0,
        "flashcannon": 1.0,
        "fusionbolt": 2.0,
        "sleeptalk": 1.0,
        "outrage": 1.0,
        "freezeshock": 1.0,
        "dragonclaw": 1.0,
        "dracometeor": 1.0
      },
      "Teammates": {
        "Palkia": 0.25,
        "Zekrom": 0.25,
        "Arceus": 0.37500010000000006,
        "Reshiram": 0.37500010000000006,
        "Forretress": 0.7500001000000001,
        "Victini": 0.8749998999999999,
        "Groudon": 0.37500010000000006,
        "Arceus-Ghost": 0.7500001000000001,
        "empty": 0.0
      }
    },
    "Ferrothorn": {
      "Abilities": { "ironbarbs": 4.0 },
      "Items": { "rockyhelmet": 4.0 },
      "Raw count": 4,
      "Spreads": {
        "Careful:252/0/0/0/252/4": 1.0,
        "Sassy:252/0/4/0/252/0": 3.0
      },
      "Checks and Counters": {},
      "Moves": {
        "spikes": 3.0,
        "powerwhip": 4.0,
        "leechseed": 4.0,
        "stealthrock": 1.0,
        "thunderwave": 1.0,
        "gyroball": 3.0
      },
      "Teammates": {
        "Latios": 0.8333332,
        "Gliscor": 1.6666668,
        "Giratina": 1.3333332,
        "Palkia": 1.0,
        "Arceus": 0.1666668,
        "Rayquaza": 0.1666668,
        "Kyogre": -0.1666668,
        "Tyranitar": 1.5,
        "Espeon": 0.6666668,
        "Excadrill": 1.1666668
      }
    },
    "Blissey": {
      "Abilities": { "naturalcure": 2.0 },
      "Items": { "leftovers": 2.0 },
      "Raw count": 2,
      "Spreads": { "Calm:4/0/252/0/252/0": 2.0 },
      "Checks and Counters": {},
      "Moves": {
        "toxic": 2.0,
        "wish": 2.0,
        "protect": 2.0,
        "seismictoss": 2.0
      },
      "Teammates": {
        "Ho-Oh": 1.8333334,
        "Groudon": 1.5833334,
        "Giratina-Origin": 1.6666666,
        "Umbreon": 1.8333334,
        "Mewtwo": 1.6666666
      }
    },
    "Dragonite": {
      "Abilities": { "innerfocus": 1.0 },
      "Items": { "dragonfang": 1.0 },
      "Raw count": 1,
      "Spreads": { "Lonely:252/252/0/4/0/0": 1.0 },
      "Checks and Counters": {},
      "Moves": {
        "dragonrush": 1.0,
        "hurricane": 1.0,
        "aquatail": 1.0,
        "dracometeor": 1.0
      },
      "Teammates": {
        "Zekrom": 0.75,
        "Raichu": 0.9166667,
        "Charizard": 0.9166667,
        "Serperior": 0.9166667,
        "Reshiram": 0.7916667
      }
    },
    "Shaymin-Sky": {
      "Abilities": { "serenegrace": 3.0 },
      "Items": { "leftovers": 1.0, "lifeorb": 1.0, "lumberry": 1.0 },
      "Raw count": 3,
      "Spreads": {
        "Modest:4/0/0/252/0/252": 1.0,
        "Timid:0/0/0/252/4/252": 1.0,
        "Timid:0/0/4/252/0/252": 1.0
      },
      "Checks and Counters": {},
      "Moves": {
        "seedflare": 3.0,
        "earthpower": 2.0,
        "gigadrain": 1.0,
        "leechseed": 1.0,
        "psychic": 1.0,
        "grasswhistle": 1.0,
        "airslash": 2.0,
        "substitute": 1.0
      },
      "Teammates": {
        "Gothitelle": 0.8749998999999999,
        "Lugia": 0.7500001000000001,
        "Weavile": 0.7500001000000001,
        "Arceus": 0.37500010000000006,
        "Kyurem-White": 0.625,
        "Omastar": 0.8749998999999999,
        "Genesect": 0.625,
        "Kyogre": 1.1249999,
        "Darkrai": 0.37500010000000006
      }
    },
    "Excadrill": {
      "Abilities": { "sandrush": 4.0, "moldbreaker": 2.0 },
      "Items": { "focussash": 1.0, "leftovers": 4.0, "lifeorb": 1.0 },
      "Raw count": 6,
      "Spreads": {
        "Jolly:4/252/0/0/0/252": 3.0,
        "Adamant:252/252/0/0/4/0": 1.0,
        "Adamant:172/252/0/0/0/84": 1.0,
        "Impish:252/252/0/0/0/0": 1.0
      },
      "Checks and Counters": {},
      "Moves": {
        "protect": 1.0,
        "rockslide": 3.0,
        "swordsdance": 4.0,
        "stealthrock": 1.0,
        "rapidspin": 6.0,
        "ironhead": 1.0,
        "drillrun": 1.0,
        "earthquake": 5.0,
        "substitute": 2.0
      },
      "Teammates": {
        "Terrakion": 0.7499998,
        "Gliscor": 1.5000002000000001,
        "Giratina": 0.9999997999999999,
        "Palkia": 1.5,
        "Giratina-Origin": -2.0000000011677344e-7,
        "Weavile": 0.5000002,
        "Shedinja": 0.7499998,
        "Arceus": -0.24999979999999988,
        "Deoxys-Attack": 0.5000002,
        "Steelix": 0.7499998,
        "Kyogre": -0.7500002000000001,
        "Tyranitar": 2.25,
        "Garchomp": 0.7499998,
        "Landorus": 0.7499998,
        "Heatran": 0.7499998,
        "Ferrothorn": 1.25,
        "Azumarill": 0.7499998,
        "Dugtrio": 0.5000002
      }
    },
    "Latios": {
      "Abilities": { "levitate": 1.0 },
      "Items": { "souldew": 1.0 },
      "Raw count": 1,
      "Spreads": { "Timid:4/0/0/252/0/252": 1.0 },
      "Checks and Counters": {},
      "Moves": {
        "thunder": 1.0,
        "energyball": 1.0,
        "psyshock": 1.0,
        "dragonpulse": 1.0
      },
      "Teammates": {
        "Ferrothorn": 0.875,
        "Arceus": 0.7916667,
        "Rayquaza": 0.7916667,
        "Espeon": 0.9166667,
        "Kyogre": 0.7083333
      }
    },
    "Gothitelle": {
      "Abilities": { "shadowtag": 1.0 },
      "Items": { "choicescarf": 1.0 },
      "Raw count": 1,
      "Spreads": { "Modest:0/0/4/252/0/252": 1.0 },
      "Checks and Counters": {},
      "Moves": { "trick": 1.0, "psychic": 1.0, "grassknot": 1.0 },
      "Teammates": {
        "Weavile": 0.9166667,
        "Omastar": 0.9583333,
        "Arceus": 0.7916667,
        "Shaymin-Sky": 0.9166667,
        "Kyogre": 0.7083333
      }
    },
    "Smeargle": {
      "Abilities": { "owntempo": 2.0 },
      "Items": { "nothing": 1.0, "focussash": 1.0 },
      "Raw count": 2,
      "Spreads": {
        "Naive:252/0/0/0/0/252": 1.0,
        "Hardy:84/84/84/84/84/84": 1.0
      },
      "Checks and Counters": {},
      "Moves": {
        "spore": 2.0,
        "batonpass": 2.0,
        "swordsdance": 1.0,
        "shellsmash": 1.0,
        "fakeout": 1.0,
        "substitute": 1.0
      },
      "Teammates": {
        "Durant": 0.9166666,
        "Dugtrio": 0.8333334,
        "Hydreigon": 0.9166666,
        "Zekrom": 0.5,
        "Darmanitan": 0.9166666,
        "Slowbro": 0.9166666,
        "Carracosta": 0.9166666,
        "Bisharp": 0.9166666,
        "Krookodile": 0.9166666,
        "Floatzel": 0.9166666
      }
    },
    "Darmanitan": {
      "Abilities": { "sheerforce": 1.0 },
      "Items": { "lifeorb": 1.0 },
      "Raw count": 1,
      "Spreads": { "Jolly:4/252/0/0/0/252": 1.0 },
      "Checks and Counters": {},
      "Moves": {
        "hammerarm": 1.0,
        "firepunch": 1.0,
        "stoneedge": 1.0,
        "earthquake": 1.0
      },
      "Teammates": {
        "Zekrom": 0.75,
        "Smeargle": 0.9166667,
        "Bisharp": 0.9583333,
        "Carracosta": 0.9583333,
        "Krookodile": 0.9583333
      }
    },
    "Kyogre": {
      "Abilities": { "drizzle": 10.0 },
      "Items": {
        "nothing": 1.0,
        "leftovers": 4.0,
        "mysticwater": 1.0,
        "choicespecs": 3.0,
        "choicescarf": 1.0
      },
      "Raw count": 10,
      "Spreads": {
        "Bold:252/0/252/0/0/4": 1.0,
        "Timid:4/0/0/252/0/252": 2.0,
        "Modest:232/0/0/252/0/24": 1.0,
        "Modest:0/0/4/252/0/252": 1.0,
        "Mild:252/4/0/252/0/0": 1.0,
        "Modest:240/0/236/0/0/32": 1.0,
        "Hardy:84/84/84/84/84/84": 2.0,
        "Modest:252/0/4/252/0/0": 1.0
      },
      "Checks and Counters": {},
      "Moves": {
        "surf": 3.0,
        "scald": 3.0,
        "blizzard": 1.0,
        "thunder": 6.0,
        "rest": 2.0,
        "calmmind": 2.0,
        "sleeptalk": 3.0,
        "aquatail": 2.0,
        "icebeam": 7.0,
        "hydropump": 4.0,
        "waterspout": 5.0,
        "earthquake": 2.0
      },
      "Teammates": {
        "Palkia": -1.5,
        "Weavile": 0.166667,
        "Zekrom": -1.5,
        "Arceus": 1.916667,
        "Arceus-Ghost": 0.166667,
        "Deoxys-Speed": 0.166667,
        "Rayquaza": 0.9166669999999999,
        "Reshiram": -1.083333,
        "Blaziken": 0.166667,
        "Darkrai": 0.9166669999999999,
        "Genesect": 0.75,
        "Ferrothorn": -0.25,
        "Shaymin-Sky": 1.166667,
        "Excadrill": -1.083333,
        "Latios": 0.583333,
        "Gothitelle": 0.583333,
        "Giratina-Origin": -0.6666669999999999,
        "Deoxys-Attack": 1.166667,
        "Espeon": 0.166667,
        "Groudon": -1.083333,
        "Lugia": 1.166667,
        "Kyurem-White": -0.25,
        "Omastar": 0.583333,
        "Kingdra": 0.583333
      }
    },
    "Giratina-Origin": {
      "Abilities": { "levitate": 5.0 },
      "Items": { "griseousorb": 5.0 },
      "Raw count": 5,
      "Spreads": {
        "Jolly:0/252/0/0/4/252": 1.0,
        "Jolly:0/252/4/0/0/252": 2.0,
        "Adamant:252/224/0/0/4/28": 1.0,
        "Naive:0/248/0/64/0/196": 1.0
      },
      "Checks and Counters": {},
      "Moves": {
        "roar": 1.0,
        "ironhead": 1.0,
        "shadowclaw": 2.0,
        "shadowforce": 1.0,
        "shadowsneak": 4.0,
        "outrage": 5.0,
        "earthquake": 4.0,
        "dracometeor": 1.0
      },
      "Teammates": {
        "Kyurem-White": 0.375,
        "Palkia": 0.75,
        "Ho-Oh": 1.5833335,
        "Zekrom": -0.25,
        "Arceus": -0.04166650000000005,
        "Deoxys-Attack": 0.5833335,
        "Kyogre": -0.45833349999999995,
        "Groudon": 0.9583335,
        "Dialga": 0.7916665,
        "Umbreon": 1.5833335,
        "Mewtwo": 1.1666665,
        "Blissey": 1.5833335,
        "Darkrai": -0.04166650000000005,
        "Excadrill": -0.04166650000000005
      }
    },
    "Pidgeot": {
      "Abilities": { "keeneye": 1.0 },
      "Items": { "leftovers": 1.0 },
      "Raw count": 1,
      "Spreads": { "Naive:0/252/0/4/0/252": 1.0 },
      "Checks and Counters": {},
      "Moves": {
        "fly": 1.0,
        "bravebird": 1.0,
        "aerialace": 1.0,
        "airslash": 1.0
      },
      "Teammates": {
        "Machamp": 0.9583333,
        "Arcanine": 0.9583333,
        "Exeggutor": 0.9583333,
        "Alakazam": 0.9583333,
        "Blastoise": 0.9583333
      }
    },
    "Regigigas": {
      "Abilities": { "slowstart": 1.0 },
      "Items": { "jabocaberry": 1.0 },
      "Raw count": 1,
      "Spreads": { "Hardy:0/0/0/252/0/252": 1.0 },
      "Checks and Counters": {},
      "Moves": {
        "focuspunch": 1.0,
        "focusblast": 1.0,
        "earthquake": 1.0,
        "superpower": 1.0
      },
      "Teammates": {
        "Mewtwo": 0.8333333,
        "Rayquaza": 0.7916667,
        "Charizard": 0.9166667,
        "Deoxys-Speed": 0.9166667,
        "Darkrai": 0.7916667
      }
    },
    "Deoxys-Attack": {
      "Abilities": { "pressure": 3.0 },
      "Items": { "focussash": 1.0, "nothing": 1.0, "blackbelt": 1.0 },
      "Raw count": 3,
      "Spreads": {
        "Hardy:92/120/92/128/76/0": 1.0,
        "Hardy:84/84/84/84/84/84": 1.0,
        "Rash:0/208/0/48/0/252": 1.0
      },
      "Checks and Counters": {},
      "Moves": {
        "spikes": 1.0,
        "thunderbolt": 1.0,
        "psychic": 1.0,
        "icepunch": 1.0,
        "gravity": 1.0,
        "poisonjab": 1.0,
        "drainpunch": 1.0,
        "stealthrock": 1.0,
        "superpower": 1.0,
        "icebeam": 1.0,
        "cosmicpower": 1.0
      },
      "Teammates": {
        "Palkia": 0.25,
        "Giratina-Origin": 0.49999989999999994,
        "Arceus": 0.37500010000000006,
        "Reshiram": 0.37500010000000006,
        "Kyogre": 1.1249999,
        "Groudon": 0.37500010000000006,
        "Lugia": 0.7500001000000001,
        "Darkrai": 0.37500010000000006,
        "Excadrill": 0.37500010000000006
      }
    },
    "Steelix": {
      "Abilities": { "sturdy": 1.0 },
      "Items": { "focussash": 1.0 },
      "Raw count": 1,
      "Spreads": { "Hardy:252/0/252/0/0/0": 1.0 },
      "Checks and Counters": {},
      "Moves": { "dragontail": 1.0, "earthquake": 1.0, "aquatail": 1.0 },
      "Teammates": {
        "Weavile": 0.9166667,
        "Azumarill": 0.9583333,
        "Shedinja": 0.9583333,
        "Garchomp": 0.9583333,
        "Excadrill": 0.7916667
      }
    },
    "Bisharp": {
      "Abilities": { "defiant": 1.0 },
      "Items": { "lifeorb": 1.0 },
      "Raw count": 1,
      "Spreads": { "Adamant:4/252/0/0/0/252": 1.0 },
      "Checks and Counters": {},
      "Moves": {
        "ironhead": 1.0,
        "swordsdance": 1.0,
        "suckerpunch": 1.0,
        "aerialace": 1.0
      },
      "Teammates": {
        "Zekrom": 0.75,
        "Darmanitan": 0.9583333,
        "Smeargle": 0.9166667,
        "Carracosta": 0.9583333,
        "Krookodile": 0.9583333
      }
    },
    "Espeon": {
      "Abilities": { "synchronize": 1.0, "magicbounce": 2.0 },
      "Items": { "focussash": 1.0, "leftovers": 2.0 },
      "Raw count": 3,
      "Spreads": { "Timid:4/0/0/252/0/252": 2.0, "Calm:0/0/0/8/252/248": 1.0 },
      "Checks and Counters": {},
      "Moves": {
        "shadowball": 2.0,
        "psychic": 2.0,
        "reflect": 1.0,
        "yawn": 1.0,
        "grassknot": 1.0,
        "psyshock": 1.0,
        "calmmind": 2.0,
        "morningsun": 1.0
      },
      "Teammates": {
        "Latios": 0.8749998999999999,
        "Raichu": 0.7500001000000001,
        "Arceus": 0.37500010000000006,
        "Rayquaza": 1.3750001,
        "Reshiram": 0.37500010000000006,
        "Serperior": 0.7500001000000001,
        "Kyogre": 0.12499989999999994,
        "Ferrothorn": 0.625,
        "Arceus-Ice": 0.8749998999999999
      }
    },
    "Krookodile": {
      "Abilities": { "moxie": 1.0 },
      "Items": { "lifeorb": 1.0 },
      "Raw count": 1,
      "Spreads": { "Jolly:4/252/0/0/0/252": 1.0 },
      "Checks and Counters": {},
      "Moves": {
        "dragonclaw": 1.0,
        "knockoff": 1.0,
        "earthquake": 1.0,
        "rockslide": 1.0
      },
      "Teammates": {
        "Zekrom": 0.75,
        "Darmanitan": 0.9583333,
        "Smeargle": 0.9166667,
        "Bisharp": 0.9583333,
        "Carracosta": 0.9583333
      }
    },
    "Machamp": {
      "Abilities": { "guts": 1.0 },
      "Items": { "leftovers": 1.0 },
      "Raw count": 1,
      "Spreads": { "Adamant:252/252/0/0/4/0": 1.0 },
      "Checks and Counters": {},
      "Moves": {
        "payback": 1.0,
        "firepunch": 1.0,
        "crosschop": 1.0,
        "closecombat": 1.0
      },
      "Teammates": {
        "Arcanine": 0.9583333,
        "Exeggutor": 0.9583333,
        "Alakazam": 0.9583333,
        "Pidgeot": 0.9583333,
        "Blastoise": 0.9583333
      }
    },
    "Landorus": {
      "Abilities": { "sandforce": 1.0 },
      "Items": { "lifeorb": 1.0 },
      "Raw count": 1,
      "Spreads": { "Jolly:4/252/0/0/0/252": 1.0 },
      "Checks and Counters": {},
      "Moves": {
        "uturn": 1.0,
        "earthquake": 1.0,
        "superpower": 1.0,
        "stoneedge": 1.0
      },
      "Teammates": {
        "Terrakion": 0.9583333,
        "Heatran": 0.9583333,
        "Tyranitar": 0.875,
        "Dugtrio": 0.9166667,
        "Excadrill": 0.7916667
      }
    },
    "Groudon": {
      "Abilities": { "drought": 6.0 },
      "Items": {
        "nothing": 1.0,
        "leftovers": 2.0,
        "earthplate": 1.0,
        "choicescarf": 2.0
      },
      "Raw count": 6,
      "Spreads": {
        "Jolly:4/252/0/0/0/252": 1.0,
        "Impish:252/4/252/0/0/0": 2.0,
        "Adamant:0/252/64/0/0/192": 2.0,
        "Hardy:84/84/84/84/84/84": 1.0
      },
      "Checks and Counters": {},
      "Moves": {
        "dragontail": 1.0,
        "earthpower": 1.0,
        "roar": 1.0,
        "earthquake": 6.0,
        "stealthrock": 2.0,
        "firepunch": 4.0,
        "toxic": 1.0,
        "hammerarm": 2.0,
        "dragonclaw": 2.0,
        "stoneedge": 3.0
      },
      "Teammates": {
        "Kyogre": -0.7500002000000001,
        "Umbreon": 1.5000002000000001,
        "Arceus-Ghost": 0.5000002,
        "Giratina": -2.0000000011677344e-7,
        "Palkia": 0.5,
        "Giratina-Origin": 0.9999997999999999,
        "Ho-Oh": 1.5000002000000001,
        "Deoxys-Attack": 0.5000002,
        "Reshiram": 1.7500002000000001,
        "Mewtwo": 1.9999997999999999,
        "Forretress": 1.5000002000000001,
        "Kyurem-Black": 0.5000002,
        "Lugia": 0.5000002,
        "Blissey": 1.5000002000000001,
        "Darkrai": -0.24999979999999988
      }
    },
    "Azumarill": {
      "Abilities": { "thickfat": 1.0 },
      "Items": { "focussash": 1.0 },
      "Raw count": 1,
      "Spreads": { "Adamant:132/0/252/0/120/4": 1.0 },
      "Checks and Counters": {},
      "Moves": {
        "protect": 1.0,
        "perishsong": 1.0,
        "aquajet": 1.0,
        "whirlpool": 1.0
      },
      "Teammates": {
        "Weavile": 0.9166667,
        "Excadrill": 0.7916667,
        "Shedinja": 0.9583333,
        "Steelix": 0.9583333,
        "Garchomp": 0.9583333
      }
    },
    "Lugia": {
      "Abilities": { "pressure": 2.0, "multiscale": 1.0 },
      "Items": { "nothing": 1.0, "leftovers": 1.0, "sitrusberry": 1.0 },
      "Raw count": 3,
      "Spreads": {
        "Sassy:152/192/0/164/0/0": 1.0,
        "Hardy:84/84/84/84/84/84": 1.0,
        "Hasty:252/4/0/0/0/252": 1.0
      },
      "Checks and Counters": {},
      "Moves": {
        "dragontail": 2.0,
        "aeroblast": 3.0,
        "extrasensory": 1.0,
        "gigadrain": 1.0,
        "psychic": 1.0,
        "roost": 1.0,
        "aerialace": 1.0,
        "hydropump": 1.0,
        "earthquake": 1.0
      },
      "Teammates": {
        "Deoxys-Attack": 0.7500001000000001,
        "Reshiram": 0.37500010000000006,
        "Kyogre": 1.1249999,
        "Genesect": 0.625,
        "Groudon": 0.37500010000000006,
        "Kyurem-White": 0.625,
        "Darkrai": 1.3750001,
        "Shaymin-Sky": 0.7500001000000001
      }
    },
    "Arceus-Ice": {
      "Abilities": { "multitype": 1.0 },
      "Items": { "icicleplate": 1.0 },
      "Raw count": 1,
      "Spreads": { "Mild:252/4/0/252/0/0": 1.0 },
      "Checks and Counters": {},
      "Moves": {
        "extremespeed": 1.0,
        "blizzard": 1.0,
        "hail": 1.0,
        "icebeam": 1.0
      },
      "Teammates": {
        "Raichu": 0.9166667,
        "Espeon": 0.9166667,
        "Reshiram": 0.7916667,
        "Serperior": 0.9166667,
        "Rayquaza": 0.7916667
      }
    },
    "Raichu": {
      "Abilities": { "static": 2.0 },
      "Items": { "electricgem": 1.0, "leftovers": 1.0 },
      "Raw count": 2,
      "Spreads": {
        "Lonely:252/0/0/252/4/0": 1.0,
        "Hasty:0/252/0/4/0/252": 1.0
      },
      "Checks and Counters": {},
      "Moves": {
        "agility": 1.0,
        "thunderbolt": 1.0,
        "electroball": 2.0,
        "volttackle": 2.0,
        "doubleedge": 1.0,
        "discharge": 1.0
      },
      "Teammates": {
        "Charizard": 0.8333334,
        "Zekrom": 0.5,
        "Rayquaza": 0.5833334,
        "Reshiram": 1.5833334,
        "Serperior": 1.8333334,
        "Arceus-Ice": 0.9166666,
        "Espeon": 0.8333334,
        "Dragonite": 0.9166666
      }
    },
    "Dugtrio": {
      "Abilities": { "arenatrap": 2.0 },
      "Items": { "focussash": 1.0, "leftovers": 1.0 },
      "Raw count": 2,
      "Spreads": { "Jolly:4/252/0/0/0/252": 2.0 },
      "Checks and Counters": {},
      "Moves": {
        "protect": 1.0,
        "honeclaws": 1.0,
        "stoneedge": 1.0,
        "suckerpunch": 2.0,
        "pursuit": 1.0,
        "earthquake": 2.0
      },
      "Teammates": {
        "Terrakion": 0.9166666,
        "Smeargle": 0.8333334,
        "Hydreigon": 0.9166666,
        "Durant": 0.9166666,
        "Slowbro": 0.9166666,
        "Tyranitar": 0.75,
        "Landorus": 0.9166666,
        "Heatran": 0.9166666,
        "Floatzel": 0.9166666,
        "Excadrill": 0.5833334
      }
    },
    "Hydreigon": {
      "Abilities": { "levitate": 1.0 },
      "Items": { "lumberry": 1.0 },
      "Raw count": 1,
      "Spreads": { "Naughty:4/252/0/252/0/0": 1.0 },
      "Checks and Counters": {},
      "Moves": {
        "outrage": 1.0,
        "surf": 1.0,
        "zenheadbutt": 1.0,
        "firefang": 1.0
      },
      "Teammates": {
        "Smeargle": 0.9166667,
        "Floatzel": 0.9583333,
        "Dugtrio": 0.9166667,
        "Durant": 0.9583333,
        "Slowbro": 0.9583333
      }
    },
    "Ho-Oh": {
      "Abilities": { "regenerator": 3.0 },
      "Items": { "leftovers": 1.0, "lifeorb": 1.0, "flameplate": 1.0 },
      "Raw count": 3,
      "Spreads": {
        "Careful:0/252/4/0/252/0": 2.0,
        "Hardy:96/252/56/104/0/0": 1.0
      },
      "Checks and Counters": {},
      "Moves": {
        "bravebird": 3.0,
        "gigadrain": 1.0,
        "tailwind": 1.0,
        "roost": 2.0,
        "sacredfire": 2.0,
        "earthquake": 2.0,
        "flamethrower": 1.0
      },
      "Teammates": {
        "Groudon": 1.3750001,
        "Giratina-Origin": 1.4999999,
        "Umbreon": 1.7500001,
        "Blissey": 1.7500001,
        "Mewtwo": 1.4999999
      }
    },
    "Arcanine": {
      "Abilities": { "flashfire": 1.0 },
      "Items": { "leftovers": 1.0 },
      "Raw count": 1,
      "Spreads": { "Adamant:252/252/0/0/4/0": 1.0 },
      "Checks and Counters": {},
      "Moves": {
        "howl": 1.0,
        "extremespeed": 1.0,
        "firefang": 1.0,
        "flareblitz": 1.0
      },
      "Teammates": {
        "Machamp": 0.9583333,
        "Pidgeot": 0.9583333,
        "Exeggutor": 0.9583333,
        "Alakazam": 0.9583333,
        "Blastoise": 0.9583333
      }
    },
    "Shedinja": {
      "Abilities": { "wonderguard": 1.0 },
      "Items": { "focussash": 1.0 },
      "Raw count": 1,
      "Spreads": { "Jolly:0/252/4/0/0/252": 1.0 },
      "Checks and Counters": {},
      "Moves": {
        "swordsdance": 1.0,
        "protect": 1.0,
        "shadowclaw": 1.0,
        "suckerpunch": 1.0
      },
      "Teammates": {
        "Weavile": 0.9166667,
        "Azumarill": 0.9583333,
        "Excadrill": 0.7916667,
        "Steelix": 0.9583333,
        "Garchomp": 0.9583333
      }
    },
    "Carracosta": {
      "Abilities": { "sturdy": 1.0 },
      "Items": { "lifeorb": 1.0 },
      "Raw count": 1,
      "Spreads": { "Adamant:252/252/0/0/4/0": 1.0 },
      "Checks and Counters": {},
      "Moves": {
        "crunch": 1.0,
        "aquajet": 1.0,
        "shellsmash": 1.0,
        "stoneedge": 1.0
      },
      "Teammates": {
        "Zekrom": 0.75,
        "Darmanitan": 0.9583333,
        "Bisharp": 0.9583333,
        "Smeargle": 0.9166667,
        "Krookodile": 0.9583333
      }
    },
    "Serperior": {
      "Abilities": { "overgrow": 5.0 },
      "Items": {
        "miracleseed": 1.0,
        "grassgem": 1.0,
        "rockyhelmet": 1.0,
        "meadowplate": 1.0,
        "leftovers": 1.0
      },
      "Raw count": 5,
      "Spreads": {
        "Timid:0/0/0/252/4/252": 1.0,
        "Hasty:0/252/0/4/0/252": 1.0,
        "Hardy:84/84/84/84/84/84": 2.0,
        "Hasty:0/4/0/252/0/252": 1.0
      },
      "Checks and Counters": {},
      "Moves": {
        "frenzyplant": 1.0,
        "sunnyday": 1.0,
        "gigadrain": 3.0,
        "mirrorcoat": 1.0,
        "dragonpulse": 1.0,
        "solarbeam": 1.0,
        "aquatail": 1.0,
        "outrage": 1.0,
        "energyball": 3.0,
        "leafstorm": 3.0,
        "leafblade": 2.0,
        "grasspledge": 1.0,
        "synthesis": 1.0
      },
      "Teammates": {
        "Raichu": 1.5833335,
        "Charizard": 0.5833335,
        "Zekrom": -0.25,
        "Rayquaza": -0.04166650000000005,
        "Reshiram": 0.9583335,
        "Arceus-Ice": 0.7916665,
        "Espeon": 0.5833335,
        "Dragonite": 0.7916665
      }
    },
    "Umbreon": {
      "Abilities": { "synchronize": 3.0 },
      "Items": { "leftovers": 3.0 },
      "Raw count": 3,
      "Spreads": {
        "Sassy:0/4/252/0/252/0": 1.0,
        "Impish:4/0/252/0/252/0": 2.0
      },
      "Checks and Counters": {},
      "Moves": {
        "curse": 1.0,
        "foulplay": 2.0,
        "wish": 1.0,
        "moonlight": 2.0,
        "suckerpunch": 1.0,
        "healbell": 2.0,
        "toxic": 3.0
      },
      "Teammates": {
        "Ho-Oh": 1.7500001,
        "Groudon": 1.3750001,
        "Giratina-Origin": 1.4999999,
        "Blissey": 1.7500001,
        "Mewtwo": 1.4999999
      }
    },
    "Forretress": {
      "Abilities": { "sturdy": 3.0 },
      "Items": { "leftovers": 2.0, "redcard": 1.0 },
      "Raw count": 3,
      "Spreads": {
        "Careful:252/0/4/0/252/0": 1.0,
        "Sassy:0/4/252/0/252/0": 1.0,
        "Bold:252/0/252/4/0/0": 1.0
      },
      "Checks and Counters": {},
      "Moves": {
        "spikes": 2.0,
        "explosion": 1.0,
        "voltswitch": 1.0,
        "stealthrock": 2.0,
        "gyroball": 1.0,
        "rapidspin": 3.0,
        "toxic": 1.0,
        "painsplit": 1.0
      },
      "Teammates": {
        "Giratina": 0.49999989999999994,
        "Palkia": 1.25,
        "Reshiram": 1.3750001,
        "Mewtwo": 0.49999989999999994,
        "Kyurem-Black": 0.7500001000000001,
        "Groudon": 1.3750001,
        "Arceus-Ghost": 0.7500001000000001
      }
    },
    "Omastar": {
      "Abilities": { "swiftswim": 1.0 },
      "Items": { "lifeorb": 1.0 },
      "Raw count": 1,
      "Spreads": { "Modest:4/0/0/252/0/252": 1.0 },
      "Checks and Counters": {},
      "Moves": {
        "hydropump": 1.0,
        "scald": 1.0,
        "earthpower": 1.0,
        "icebeam": 1.0
      },
      "Teammates": {
        "Weavile": 0.9166667,
        "Gothitelle": 0.9583333,
        "Arceus": 0.7916667,
        "Shaymin-Sky": 0.9166667,
        "Kyogre": 0.7083333
      }
    },
    "Alakazam": {
      "Abilities": { "synchronize": 1.0, "magicguard": 1.0 },
      "Items": { "nothing": 1.0, "leftovers": 1.0 },
      "Raw count": 2,
      "Spreads": {
        "Careful:76/48/40/44/48/252": 1.0,
        "Hasty:0/4/0/252/0/252": 1.0
      },
      "Checks and Counters": {},
      "Moves": {
        "psybeam": 1.0,
        "barrier": 2.0,
        "shadowball": 1.0,
        "psychic": 1.0,
        "focusblast": 1.0,
        "psychocut": 1.0,
        "recover": 1.0
      },
      "Teammates": {
        "Machamp": 0.9166666,
        "Arcanine": 0.9166666,
        "Exeggutor": 0.9166666,
        "Pidgeot": 0.9166666,
        "Blastoise": 0.9166666
      }
    },
    "Victini": {
      "Abilities": { "victorystar": 2.0 },
      "Items": { "nothing": 1.0, "charcoal": 1.0 },
      "Raw count": 2,
      "Spreads": {
        "Hardy:136/136/0/236/0/0": 1.0,
        "Impish:96/87/80/100/50/94": 1.0
      },
      "Checks and Counters": {},
      "Moves": {
        "protect": 1.0,
        "blueflare": 2.0,
        "gigaimpact": 1.0,
        "vcreate": 1.0,
        "flamecharge": 1.0,
        "fireblast": 1.0,
        "firepunch": 1.0
      },
      "Teammates": {
        "Kyurem-Black": 0.8333334,
        "Zekrom": 0.5,
        "Arceus": 0.5833334,
        "empty": 0.0
      }
    },
    "Dialga": {
      "Abilities": { "pressure": 1.0 },
      "Items": { "adamantorb": 1.0 },
      "Raw count": 1,
      "Spreads": { "Hasty:0/0/0/252/4/252": 1.0 },
      "Checks and Counters": {},
      "Moves": {
        "aurasphere": 1.0,
        "flashcannon": 1.0,
        "roaroftime": 1.0,
        "dragonpulse": 1.0
      },
      "Teammates": {
        "Kyurem-White": 0.875,
        "Zekrom": 0.75,
        "Darkrai": 0.7916667,
        "Palkia": 0.75,
        "Giratina-Origin": 0.8333333
      }
    },
    "Floatzel": {
      "Abilities": { "waterveil": 1.0 },
      "Items": { "focussash": 1.0 },
      "Raw count": 1,
      "Spreads": { "Hardy:4/0/0/252/0/252": 1.0 },
      "Checks and Counters": {},
      "Moves": {
        "hydropump": 1.0,
        "agility": 1.0,
        "batonpass": 1.0,
        "substitute": 1.0
      },
      "Teammates": {
        "Hydreigon": 0.9583333,
        "Smeargle": 0.9166667,
        "Slowbro": 0.9583333,
        "Durant": 0.9583333,
        "Dugtrio": 0.9166667
      }
    },
    "Darkrai": {
      "Abilities": { "baddreams": 6.0 },
      "Items": {
        "nothing": 1.0,
        "leftovers": 2.0,
        "dreadplate": 1.0,
        "widelens": 1.0,
        "darkgem": 1.0
      },
      "Raw count": 6,
      "Spreads": {
        "Hardy:84/84/84/84/84/84": 1.0,
        "Modest:0/0/4/252/0/252": 1.0,
        "Timid:252/0/0/4/0/252": 1.0,
        "Hardy:172/0/132/148/56/0": 1.0,
        "Hardy:0/0/0/0/252/252": 1.0,
        "Timid:0/0/0/252/4/252": 1.0
      },
      "Checks and Counters": {},
      "Moves": {
        "darkvoid": 4.0,
        "knockoff": 1.0,
        "blizzard": 1.0,
        "darkpulse": 4.0,
        "nightshade": 1.0,
        "foulplay": 1.0,
        "thunder": 2.0,
        "focusblast": 3.0,
        "spacialrend": 2.0,
        "payback": 1.0,
        "dreameater": 2.0,
        "toxic": 1.0,
        "quickattack": 1.0
      },
      "Teammates": {
        "Lugia": 1.5000002000000001,
        "Mewtwo": -2.0000000011677344e-7,
        "Arceus": -0.24999979999999988,
        "Charizard": 0.5000002,
        "Palkia": -0.5,
        "Giratina-Origin": -2.0000000011677344e-7,
        "Deoxys-Attack": 0.5000002,
        "Zekrom": 0.5,
        "Regigigas": 0.7499998,
        "Rayquaza": 0.7500002000000001,
        "Reshiram": -0.24999979999999988,
        "Blaziken": 0.5000002,
        "Kyurem-White": 1.25,
        "Shaymin-Sky": 0.5000002,
        "Genesect": 0.25,
        "Dialga": 0.7499998,
        "Groudon": -0.24999979999999988,
        "Kyogre": 1.2499997999999999,
        "Deoxys-Speed": 0.5000002
      }
    },
    "Kingdra": {
      "Abilities": { "swiftswim": 1.0 },
      "Items": { "lifeorb": 1.0 },
      "Raw count": 1,
      "Spreads": { "Modest:32/0/8/252/0/216": 1.0 },
      "Checks and Counters": {},
      "Moves": {
        "hydropump": 1.0,
        "substitute": 1.0,
        "dracometeor": 1.0,
        "dragonpulse": 1.0
      },
      "Teammates": {
        "Arceus-Ghost": 0.9166667,
        "Rayquaza": 0.7916667,
        "Genesect": 0.875,
        "Deoxys-Speed": 0.9166667,
        "Kyogre": 0.7083333
      }
    }
  }
}
